launchflow/__init__.py
launchflow/backend.py
launchflow/exceptions.py
launchflow/fastapi.py
launchflow/flask.py
launchflow/gcp_clients.py
launchflow/generic_clients.py
launchflow/locks.py
launchflow/logger.py
launchflow/node.py
launchflow/py.typed
launchflow/resource.py
launchflow/service.py
launchflow/tofu.py
launchflow/utils.py
launchflow/validation.py
launchflow/version.py
launchflow/aws/__init__.py
launchflow/aws/acm.py
launchflow/aws/alb.py
launchflow/aws/api_gateway.py
launchflow/aws/codebuild_project.py
launchflow/aws/ec2.py
launchflow/aws/ecr_repository.py
launchflow/aws/ecs_cluster.py
launchflow/aws/ecs_fargate.py
launchflow/aws/ecs_fargate_container.py
launchflow/aws/elastic_ip.py
launchflow/aws/elasticache.py
launchflow/aws/lambda_event_mapping.py
launchflow/aws/lambda_function.py
launchflow/aws/lambda_service.py
launchflow/aws/launchflow_cloud_releaser.py
launchflow/aws/nat_gateway.py
launchflow/aws/rds.py
launchflow/aws/rds_postgres.py
launchflow/aws/resource.py
launchflow/aws/s3.py
launchflow/aws/secrets_manager.py
launchflow/aws/service.py
launchflow/aws/shared.py
launchflow/aws/sqs.py
launchflow/aws/utils.py
launchflow/builds/__init__.py
launchflow/builds/ecr_builder.py
launchflow/cache/__init__.py
launchflow/cache/launchflow_tmp.py
launchflow/cli/__init__.py
launchflow/cli/ast_search.py
launchflow/cli/constants.py
launchflow/cli/main.py
launchflow/cli/project_gen.py
launchflow/cli/resource_utils.py
launchflow/cli/service_utils.py
launchflow/cli/utils.py
launchflow/cli/utyper.py
launchflow/cli/accounts/__init__.py
launchflow/cli/accounts/account_commands.py
launchflow/cli/cloud/cloud_commands.py
launchflow/cli/environments/__init__.py
launchflow/cli/environments/environment_commands.py
launchflow/cli/gen/__init__.py
launchflow/cli/gen/template.py
launchflow/cli/gen/templates/__init__.py
launchflow/cli/gen/templates/django/__init__.py
launchflow/cli/gen/templates/django/django_template.py
launchflow-0.4.14.dist-info/licenses/LICENSE
launchflow-0.4.14.dist-info/METADATA
launchflow-0.4.14.dist-info/WHEEL
launchflow-0.4.14.dist-info/entry_points.txt
launchflow-0.4.14.dist-info/top_level.txt
launchflow-0.4.14.dist-info/RECORD
