Metadata-Version: 2.4
Name: launchflow
Version: 0.4.14
Summary: Python-native infrastructure for the cloud: LaunchFlow provides a Python SDK that automatically creates and connects to production-ready infrastructure (such as Postgres, Redis, etc..) in your own cloud account. LaunchFlow completely removes the need for DevOps allowing you to focus on your application logic.
Author-email: CalebTVanDyke <caleb@launchflow.com>, Josh Tanke <josh@launchflow.com>, Michael Noronha <michael@launchflow.com>
License:                     GNU AFFERO GENERAL PUBLIC LICENSE
Classifier: Operating System :: OS Independent
Requires-Python: >=3.9
License-File: LICENSE
Requires-Dist: beaupy
Requires-Dist: rich
Requires-Dist: toml
Requires-Dist: pyyaml
Requires-Dist: pathspec
Requires-Dist: pydantic>=2.0
Requires-Dist: deepdiff!=8.0.0
Requires-Dist: typer
Requires-Dist: requests
Requires-Dist: httpx
Requires-Dist: uvloop
Requires-Dist: Jinja2
Requires-Dist: docker
Requires-Dist: pyjwt
Requires-Dist: terminaltexteffects
Requires-Dist: setuptools
Requires-Dist: posthog
Requires-Dist: kubernetes
Provides-Extra: gcp
Requires-Dist: cloud-sql-python-connector; extra == "gcp"
Requires-Dist: google-cloud-storage; extra == "gcp"
Requires-Dist: google-cloud-resource-manager; extra == "gcp"
Requires-Dist: google-api-python-client; extra == "gcp"
Requires-Dist: google-cloud-bigquery; extra == "gcp"
Requires-Dist: google-cloud-secret-manager; extra == "gcp"
Requires-Dist: google-cloud-pubsub; extra == "gcp"
Requires-Dist: google-cloud-billing; extra == "gcp"
Requires-Dist: google-cloud-compute; extra == "gcp"
Requires-Dist: google-cloud-build; extra == "gcp"
Requires-Dist: google-cloud-run; extra == "gcp"
Requires-Dist: google-cloud-tasks; extra == "gcp"
Requires-Dist: google-cloud-service-usage; extra == "gcp"
Requires-Dist: google-cloud-compute; extra == "gcp"
Requires-Dist: google-cloud-container; extra == "gcp"
Provides-Extra: aws
Requires-Dist: boto3; extra == "aws"
Provides-Extra: dev
Requires-Dist: pytest>=7.4.4; extra == "dev"
Requires-Dist: pytest-asyncio; extra == "dev"
Requires-Dist: sqlalchemy[asyncio]>=2.0.27; extra == "dev"
Requires-Dist: pytest-httpx==0.30.0; extra == "dev"
Requires-Dist: boto3-stubs[secretsmanager]; extra == "dev"
Requires-Dist: freezegun; extra == "dev"
Requires-Dist: moto; extra == "dev"
Requires-Dist: mypy; extra == "dev"
Requires-Dist: types-requests; extra == "dev"
Requires-Dist: types-pyyaml; extra == "dev"
Requires-Dist: types-setuptools; extra == "dev"
Requires-Dist: types-toml; extra == "dev"
Requires-Dist: types-redis; extra == "dev"
Dynamic: license-file
